plugin_sdk_automation/__init__.py
plugin_sdk_automation/main.py
plugin_sdk_automation/handlers/__init__.py
plugin_sdk_automation/handlers/docker_handler.py
plugin_sdk_automation/handlers/props_handler.py
plugin_sdk_automation-1.1.5.dist-info/METADATA
plugin_sdk_automation-1.1.5.dist-info/WHEEL
plugin_sdk_automation-1.1.5.dist-info/entry_points.txt
plugin_sdk_automation-1.1.5.dist-info/top_level.txt
plugin_sdk_automation-1.1.5.dist-info/RECORD
